optuna_async_helper/__init__.py
optuna_async_helper-0.7.1.dist-info/METADATA
optuna_async_helper-0.7.1.dist-info/WHEEL
optuna_async_helper-0.7.1.dist-info/licenses/LICENSE
optuna_async_helper-0.7.1.dist-info/RECORD
