Metadata-Version: 2.4
Name: optuna-async-helper
Version: 0.7.1
Summary: A Helper Library for Optuna Async Optimization
Project-URL: repository, https://github.com/lucidfrontier45/optuna-async-helper
Author-email: 杜 世橋 Du Shiqiao <lucidfrontier.45@gmail.com>
License: MIT
License-File: LICENSE
Classifier: Intended Audience :: Developers
Classifier: Intended Audience :: Science/Research
Classifier: License :: OSI Approved :: MIT License
Classifier: Programming Language :: Python :: 3
Classifier: Programming Language :: Python :: 3 :: Only
Classifier: Programming Language :: Python :: 3.11
Classifier: Programming Language :: Python :: 3.12
Classifier: Topic :: Scientific/Engineering
Classifier: Topic :: Scientific/Engineering :: Artificial Intelligence
Classifier: Topic :: Scientific/Engineering :: Mathematics
Classifier: Topic :: Software Development
Classifier: Topic :: Software Development :: Libraries
Classifier: Topic :: Software Development :: Libraries :: Python Modules
Requires-Python: >=3.11
Requires-Dist: joblib>=1.3.2
Requires-Dist: optuna>=4.0.0
Requires-Dist: pydantic>=2.6.1
